higdon.py
higdon-0.1.2.dist-info/LICENSE
higdon-0.1.2.dist-info/METADATA
higdon-0.1.2.dist-info/WHEEL
higdon-0.1.2.dist-info/entry_points.txt
higdon-0.1.2.dist-info/top_level.txt
higdon-0.1.2.dist-info/RECORD
