Metadata-Version: 2.1
Name: higdon
Version: 0.1.2
Summary: Generate calendar files from Hal Higdon training plans.
Home-page: https://github.com/baldwint/higdon
Author: Tom Baldwin
Author-email: baldwint@baldwint.com
License: MIT
Platform: UNKNOWN
Classifier: Development Status :: 3 - Alpha
Classifier: Topic :: Utilities
Classifier: License :: OSI Approved :: MIT License
Classifier: Programming Language :: Python :: 3 :: Only
Classifier: Programming Language :: Python :: 3.7
Requires-Dist: python-dateutil
Requires-Dist: icalendar
Requires-Dist: requests
Requires-Dist: beautifulsoup4
